scipy_openblas64/__init__.py
scipy_openblas64/__main__.py
scipy_openblas64/include/cblas.h
scipy_openblas64/include/f77blas.h
scipy_openblas64/include/lapack.h
scipy_openblas64/include/lapacke.h
scipy_openblas64/include/lapacke_config.h
scipy_openblas64/include/lapacke_mangling.h
scipy_openblas64/include/lapacke_utils.h
scipy_openblas64/include/openblas_config.h
scipy_openblas64/lib/libgcc_s-0cd532bd.so.1
scipy_openblas64/lib/libgfortran-2c33b284.so.5.0.0
scipy_openblas64/lib/libquadmath-bb76a5fc.so.0.0.0
scipy_openblas64/lib/libscipy_openblas64_.so
scipy_openblas64/lib/cmake/openblas/OpenBLASConfig.cmake
scipy_openblas64/lib/cmake/openblas/OpenBLASConfigVersion.cmake
scipy_openblas64/lib/pkgconfig/scipy-openblas.pc
scipy_openblas64-0.3.31.22.1.dist-info/METADATA
scipy_openblas64-0.3.31.22.1.dist-info/WHEEL
scipy_openblas64-0.3.31.22.1.dist-info/entry_points.txt
scipy_openblas64-0.3.31.22.1.dist-info/top_level.txt
scipy_openblas64-0.3.31.22.1.dist-info/RECORD
scipy_openblas64-0.3.31.22.1.dist-info/licenses/LICENSE.txt
scipy_openblas64-0.3.31.22.1.dist-info/sboms/auditwheel.cdx.json
