Metadata-Version: 2.4
Name: scipy-openblas64
Version: 0.3.31.22.1
Summary: Provides OpenBLAS for python packaging
License: BSD 2-Clause License
Project-URL: homepage, https://github.com/MacPython/openblas-libs
Project-URL: upstream, https://github.com/OpenMathLib/OpenBLAS
Classifier: Development Status :: 5 - Production/Stable
Classifier: Programming Language :: C++
Classifier: License :: OSI Approved :: BSD License
Requires-Python: >=3.7
License-File: LICENSE.txt
Dynamic: license-file
